crudviewset/__init__.py
crudviewset/constants.py
crudviewset/utils.py
crudviewset/valueobjects.py
crudviewset/viewsets.py
crudviewset/templates/.DS_Store
crudviewset/templates/crudviewset/.DS_Store
crudviewset/templates/crudviewset/delete.html
crudviewset/templates/crudviewset/detail.html
crudviewset/templates/crudviewset/form.html
crudviewset/templates/crudviewset/list.html
crudviewset/templates/crudviewset/base/base.html
crudviewset/templates/crudviewset/base/footer.html
crudviewset/templates/crudviewset/base/header.html
django_crudviewset-0.1.2.dist-info/METADATA
django_crudviewset-0.1.2.dist-info/RECORD
django_crudviewset-0.1.2.dist-info/WHEEL
django_crudviewset-0.1.2.dist-info/top_level.txt
