Metadata-Version: 2.1
Name: django-crudviewset
Version: 0.1.2
Summary: Django CRUDViewSet
Home-page: https://github.com/yusk/django-crudviewset
Author: yusk
Author-email: tdfagamdb@yahoo.co.jp
License: MIT License
Platform: UNKNOWN
Classifier: Environment :: Web Environment
Classifier: Framework :: Django
Classifier: Framework :: Django :: 2.0
Classifier: Intended Audience :: Developers
Classifier: License :: OSI Approved :: MIT License
Classifier: Programming Language :: Python
Classifier: Programming Language :: Python :: 3
Classifier: Programming Language :: Python :: 3.6
Classifier: Topic :: Internet :: WWW/HTTP
Classifier: Topic :: Internet :: WWW/HTTP :: Dynamic Content
Requires-Dist: django
